jml/__init__.py
jml/__main__.py
jml/config.py
jml/console.py
jml/jml.py
jml/jml.toml
jml/project.py
jml/versions.py
jml/utils/__init__.py
jml/utils/files.py
jml-0.4.3.dist-info/METADATA
jml-0.4.3.dist-info/WHEEL
jml-0.4.3.dist-info/entry_points.txt
jml-0.4.3.dist-info/RECORD
