Metadata-Version: 2.4
Name: jml
Version: 0.4.3
Summary: Ein Tool um Projektversionen zu generieren
Project-URL: Homepage, http://github.com/jneug/jml
Project-URL: Repository, http://github.com/jneug/jml
Author-email: "J. Neugebauer" <ngb@helmholtz-bi.de>
License-Expression: MIT
Classifier: Programming Language :: Python :: 3
Requires-Python: ~=3.8
Requires-Dist: click>=8.0.3
Requires-Dist: rich>=14.0.0
Requires-Dist: toml>=0.10.2
